texrelenv/__init__.py
texrelenv/color.py
texrelenv/environment.py
texrelenv/exceptions.py
texrelenv-0.1.3.dist-info/LICENSE
texrelenv-0.1.3.dist-info/METADATA
texrelenv-0.1.3.dist-info/WHEEL
texrelenv-0.1.3.dist-info/RECORD
