Metadata-Version: 2.1
Name: texrelenv
Version: 0.1.3
Summary: A Python package for generating data sets based on Hugh Perkins' TexRel (https://arxiv.org/abs/2105.12804)
License: MIT
Author: Nicholas Bailey
Author-email: nicholasbailey87@gmail.com
Requires-Python: >=3.12,<4.0
Classifier: License :: OSI Approved :: MIT License
Classifier: Programming Language :: Python :: 3
Classifier: Programming Language :: Python :: 3.12
Classifier: Programming Language :: Python :: 3.13
Requires-Dist: numpy (>=2.2.0,<3.0.0)
Requires-Dist: toml (>=0.10.2,<0.11.0)
